{
  "data": {
    "article": {},
    "attachments": {},
    "author_id": "1776553425934909440",
    "conversation_id": "2023358418137043046",
    "created_at": "2026-02-17T11:43:11.000Z",
    "edit_controls": {
      "editable_until": "2026-02-17T12:43:11.000Z",
      "edits_remaining": 5,
      "is_edit_eligible": false
    },
    "edit_history_tweet_ids": [
      "2023724906123551076"
    ],
    "entities": {
      "mentions": [
        {
          "end": 15,
          "id": "3041210477",
          "start": 0,
          "username": "scatasianLeung"
        },
        {
          "end": 27,
          "id": "797439291752378368",
          "start": 16,
          "username": "lover_ning"
        }
      ]
    },
    "geo": {},
    "id": "2023724906123551076",
    "in_reply_to_user_id": "3041210477",
    "lang": "zh",
    "note_tweet": {
      "entities": {}
    },
    "possibly_sensitive": false,
    "public_metrics": {
      "bookmark_count": 0,
      "impression_count": 0,
      "like_count": 0,
      "quote_count": 0,
      "reply_count": 0,
      "retweet_count": 0
    },
    "referenced_tweets": [
      {
        "id": "2023494876957163604",
        "type": "replied_to"
      }
    ],
    "reply_settings": "everyone",
    "text": "@scatasianLeung @lover_ning 也好吓人"
  },
  "includes": {
    "tweets": [
      {
        "article": {},
        "attachments": {},
        "author_id": "1776553425934909440",
        "conversation_id": "2023358418137043046",
        "created_at": "2026-02-17T11:43:11.000Z",
        "edit_controls": {
          "editable_until": "2026-02-17T12:43:11.000Z",
          "edits_remaining": 5,
          "is_edit_eligible": false
        },
        "edit_history_tweet_ids": [
          "2023724906123551076"
        ],
        "entities": {
          "mentions": [
            {
              "end": 15,
              "id": "3041210477",
              "start": 0,
              "username": "scatasianLeung"
            },
            {
              "end": 27,
              "id": "797439291752378368",
              "start": 16,
              "username": "lover_ning"
            }
          ]
        },
        "geo": {},
        "id": "2023724906123551076",
        "in_reply_to_user_id": "3041210477",
        "lang": "zh",
        "note_tweet": {
          "entities": {}
        },
        "possibly_sensitive": false,
        "public_metrics": {
          "bookmark_count": 0,
          "impression_count": 0,
          "like_count": 0,
          "quote_count": 0,
          "reply_count": 0,
          "retweet_count": 0
        },
        "referenced_tweets": [
          {
            "id": "2023494876957163604",
            "type": "replied_to"
          }
        ],
        "reply_settings": "everyone",
        "text": "@scatasianLeung @lover_ning 也好吓人"
      },
      {
        "article": {},
        "attachments": {},
        "author_id": "3041210477",
        "conversation_id": "2023358418137043046",
        "created_at": "2026-02-16T20:29:08.000Z",
        "edit_controls": {
          "editable_until": "2026-02-16T21:29:08.000Z",
          "edits_remaining": 5,
          "is_edit_eligible": false
        },
        "edit_history_tweet_ids": [
          "2023494876957163604"
        ],
        "entities": {
          "mentions": [
            {
              "end": 16,
              "id": "1776553425934909440",
              "start": 0,
              "username": "hshshshshs88082"
            },
            {
              "end": 28,
              "id": "797439291752378368",
              "start": 17,
              "username": "lover_ning"
            }
          ]
        },
        "geo": {},
        "id": "2023494876957163604",
        "in_reply_to_user_id": "1776553425934909440",
        "lang": "zh",
        "note_tweet": {
          "entities": {}
        },
        "possibly_sensitive": false,
        "public_metrics": {
          "bookmark_count": 0,
          "impression_count": 138,
          "like_count": 0,
          "quote_count": 0,
          "reply_count": 0,
          "retweet_count": 0
        },
        "referenced_tweets": [
          {
            "id": "2023470448592449832",
            "type": "replied_to"
          }
        ],
        "reply_settings": "everyone",
        "text": "@hshshshshs88082 @lover_ning 不到这个男人头的一半"
      }
    ],
    "users": [
      {
        "created_at": "2024-04-06T10:12:13.000Z",
        "description": "吵吵的小女孩 。",
        "id": "1776553425934909440",
        "name": "烤焦的披萨",
        "profile_image_url": "https://pbs.twimg.com/profile_images/2023640257380700160/zpiWxBO__normal.jpg",
        "protected": false,
        "public_metrics": {
          "followers_count": 33,
          "following_count": 65,
          "like_count": 79,
          "listed_count": 1,
          "media_count": 89,
          "tweet_count": 617
        },
        "username": "hshshshshs88082",
        "verified": false
      },
      {
        "created_at": "2015-02-16T18:36:36.000Z",
        "description": "喜欢很多不同的东西",
        "id": "3041210477",
        "location": "顺德乐从， 南海桂城",
        "name": "bicurious_canton",
        "profile_image_url": "https://pbs.twimg.com/profile_images/1989258054701871104/5yGpSuBk_normal.jpg",
        "protected": false,
        "public_metrics": {
          "followers_count": 233,
          "following_count": 1049,
          "like_count": 16194,
          "listed_count": 3,
          "media_count": 12,
          "tweet_count": 3646
        },
        "username": "scatasianLeung",
        "verified": false
      },
      {
        "created_at": "2016-11-12T14:01:57.000Z",
        "description": "本号偏猎奇向，谨慎关注 / 头像是本人",
        "entities": {
          "url": {
            "urls": [
              {
                "display_url": "onion03.vip/?channelid=145…",
                "end": 23,
                "expanded_url": "https://onion03.vip?channelid=14532&tid=562324&type=7&system=1",
                "start": 0,
                "url": "https://t.co/V6J2FWCXht"
              }
            ]
          }
        },
        "id": "797439291752378368",
        "location": "免费VPN👉🏼",
        "name": "SUZU",
        "pinned_tweet_id": "1970317413502853194",
        "profile_image_url": "https://pbs.twimg.com/profile_images/1746648879364501505/tSGXif8I_normal.jpg",
        "protected": false,
        "public_metrics": {
          "followers_count": 269593,
          "following_count": 104,
          "like_count": 32868,
          "listed_count": 469,
          "media_count": 3435,
          "tweet_count": 28448
        },
        "url": "https://t.co/V6J2FWCXht",
        "username": "lover_ning",
        "verified": false
      }
    ]
  }
}